setup.py
insight_python/com/__init__.py
insight_python/com/data_handle.py
insight_python/com/log_handle.py
insight_python/com/insight/common.py
insight_python/com/insight/market_service.py
insight_python/com/insight/playback.py
insight_python/com/insight/query.py
insight_python/com/insight/subscribe.py
insight_python/com/interface/mdc_enumerated_mapping_table.py
insight_python/com/interface/mdc_gateway_base_define.py
insight_python/com/interface/mdc_gateway_head.py
insight_python/com/interface/mdc_gateway_interface.py
insight_python/com/interface/mdc_playback_handledata_class.py
insight_python/com/interface/mdc_query_async_handle_data_class.py
insight_python/com/interface/mdc_query_sync_handle_data_class.py
insight_python/com/interface/mdc_query_sync_handle_method.py
insight_python/com/interface/mdc_query_sync_mapping_table.py
insight_python/com/interface/mdc_recvdata_interface.py
insight_python/com/interface/mdc_subscribe_handledata_class.py
insight_python/com/cert/HTISCA.crt
insight_python/com/cert/InsightClientCert.pem
insight_python/com/cert/InsightClientKeyPkcs8.pem
insight_python/com/cert/service-insight_htsc_com_cn_int_2022.cer
insight_python/com/libs/python310/ACE.dll
insight_python/com/libs/python310/ACE_SSL.dll
insight_python/com/libs/python310/_mdc_gateway_client.pyd
insight_python/com/libs/python310/libeay32.dll
insight_python/com/libs/python310/mdc_gateway_client.py
insight_python/com/libs/python310/ssleay32.dll
insight_python/com/libs/python36/ACE.dll
insight_python/com/libs/python36/ACE_SSL.dll
insight_python/com/libs/python36/_mdc_gateway_client.pyd
insight_python/com/libs/python36/libeay32.dll
insight_python/com/libs/python36/mdc_gateway_client.py
insight_python/com/libs/python36/ssleay32.dll
insight_python/com/libs/python37/ACE.dll
insight_python/com/libs/python37/ACE_SSL.dll
insight_python/com/libs/python37/_mdc_gateway_client.pyd
insight_python/com/libs/python37/libeay32.dll
insight_python/com/libs/python37/mdc_gateway_client.py
insight_python_win.egg-info/PKG-INFO
insight_python_win.egg-info/SOURCES.txt
insight_python_win.egg-info/dependency_links.txt
insight_python_win.egg-info/top_level.txt